beehive/__init__.py
beehive/constants.py
beehive/message.py
beehive/cookbook/__init__.py
beehive/invokable/__init__.py
beehive/invokable/agent.py
beehive/invokable/base.py
beehive/invokable/beehive.py
beehive/invokable/debate.py
beehive/invokable/ensemble.py
beehive/invokable/executor.py
beehive/invokable/langchain_agent.py
beehive/invokable/team.py
beehive/invokable/types.py
beehive/invokable/utils.py
beehive/memory/__init__.py
beehive/memory/db_storage.py
beehive/memory/feedback_storage.py
beehive/mixins/__init__.py
beehive/mixins/langchain.py
beehive/models/__init__.py
beehive/models/base.py
beehive/models/openai_embedder.py
beehive/models/openai_model.py
beehive/prompts/__init__.py
beehive/prompts/ask_question_prompt.txt
beehive/prompts/context_prompt_concise.txt
beehive/prompts/context_prompt_full.txt
beehive/prompts/debate_judge_prompt.txt
beehive/prompts/debate_judge_summary_prompt.txt
beehive/prompts/ensemble_func_summary_prompt.txt
beehive/prompts/ensemble_llm_summary_prompt.txt
beehive/prompts/evaluation_prompt.txt
beehive/prompts/feedback_prompt.txt
beehive/prompts/long_form_debate_prompt.txt
beehive/prompts/model_error_prompt.txt
beehive/prompts/router_prompting_prompt.txt
beehive/prompts/router_question_prompt.txt
beehive/prompts/router_routing_prompt.txt
beehive/prompts/short_form_debate_prompt.txt
beehive/prompts/synthesizer_prompt.txt
beehive/tests/__init__.py
beehive/tests/conftest.py
beehive/tests/mocks.py
beehive/tests/parser_common.py
beehive/tests/parser_google_fns.py
beehive/tests/parser_sphinx_fns.py
beehive/tests/test_agents.py
beehive/tests/test_beehives.py
beehive/tests/test_db_storage.py
beehive/tests/test_feedback_storage.py
beehive/tests/test_langchain_agents.py
beehive/tests/test_parsers.py
beehive/tests/test_prompts.py
beehive/tests/test_teams.py
beehive/tests/test_tools.py
beehive/tools/__init__.py
beehive/tools/base.py
beehive/tools/google.py
beehive/tools/parser.py
beehive/tools/sphinx.py
beehive/tools/types.py
beehive_ai-0.0.2.dist-info/LICENSE
beehive_ai-0.0.2.dist-info/METADATA
beehive_ai-0.0.2.dist-info/WHEEL
beehive_ai-0.0.2.dist-info/top_level.txt
beehive_ai-0.0.2.dist-info/RECORD
