Metadata-Version: 2.1
Name: beehive-ai
Version: 0.0.2
Summary: 🐝 Create powerful, collaborative AI applications.
Author: Mihir Trivedi
Author-email: mtrivedi50@gmail.com
License: Apache-2.0
Platform: unix
Platform: linux
Platform: osx
Platform: win32
Classifier: Programming Language :: Python :: 3.12
Requires-Python: >=3.11
License-File: LICENSE
Requires-Dist: Jinja2==3.1.4
Requires-Dist: openai==1.40.5
Requires-Dist: pydantic==2.8.2
Requires-Dist: pydantic-settings==2.5.2
Requires-Dist: pydantic-core==2.20.1
Requires-Dist: rich==13.7.1
Requires-Dist: SQLAlchemy==2.0.32
Requires-Dist: sqlmodel==0.0.21
Requires-Dist: chromadb==0.5.11
Requires-Dist: langchain==0.3.1
Requires-Dist: langchain-community==0.3.1
Requires-Dist: langchain-core==0.3.6
Requires-Dist: langchain-experimental==0.3.2
Requires-Dist: langchain-openai==0.2.1
Requires-Dist: langchain-text-splitters==0.3.0
Requires-Dist: nltk==3.9.1
Provides-Extra: dev
Requires-Dist: mypy>=1.11; extra == "dev"
Requires-Dist: pytest>=7; extra == "dev"
Requires-Dist: mkdocs==1.6.1; extra == "dev"
Requires-Dist: mkdocs-material==9.5.39; extra == "dev"
Requires-Dist: sqlalchemy2-stubs==0.0.2a38; extra == "dev"
Requires-Dist: pre-commit==3.8.0; extra == "dev"
Requires-Dist: twine==5.1.1; extra == "dev"
Requires-Dist: build==1.2.2.post1; extra == "dev"
Requires-Dist: ipykernel==6.29.5; extra == "dev"
